shinymdc/__init__.py
shinymdc/_latexmk.py
shinymdc/_liquid.py
shinymdc/_pandoc.py
shinymdc/_templates.py
shinymdc/_version.py
shinymdc/resources/dynamic/addappendices.tex
shinymdc/resources/dynamic/authsetup.tex
shinymdc/resources/dynamic/authsetupshort.tex
shinymdc/resources/dynamic/dblfloatsetup.tex
shinymdc/resources/dynamic/pdfsetup.tex
shinymdc/resources/static/bibnonatsetup.tex
shinymdc/resources/static/bibnosupersetup.tex
shinymdc/resources/static/bibsupersetup.tex
shinymdc/resources/static/floatsetup.tex
shinymdc/resources/static/iccv/bibstyle.bst
shinymdc/resources/static/iccv/esopic.sty
shinymdc/resources/static/iccv/everyshi.sty
shinymdc/resources/static/iccv/iccv.sty
shinymdc/resources/static/iclr/bibstyle.bst
shinymdc/resources/static/iclr/iclr.sty
shinymdc/resources/static/iclr/mathcommands.tex
shinymdc/resources/static/icml/bibstyle.bst
shinymdc/resources/static/icml/icml.sty
shinymdc/resources/static/mathsetup.tex
shinymdc/resources/static/miscsetup.tex
shinymdc/resources/static/neurips/neurips.sty
shinymdc/resources/static/reqsetup.tex
shinymdc/shinymdc.py
shinymdc/templates/basic.tex
shinymdc/templates/iccv.tex
shinymdc/templates/iclr.tex
shinymdc/templates/icml.tex
shinymdc/templates/neurips.tex
shinymdc/templates/spacious.tex
shinymdc/templates/standalone.tex
shinymdc/templates/stylish.tex
shiny_mdc-1.9.0.dist-info/LICENSE
shiny_mdc-1.9.0.dist-info/METADATA
shiny_mdc-1.9.0.dist-info/WHEEL
shiny_mdc-1.9.0.dist-info/entry_points.txt
shiny_mdc-1.9.0.dist-info/RECORD
