Metadata-Version: 2.1
Name: shiny-mdc
Version: 1.9.0
Summary: Tool to compile markdown files to tex/pdf using pandoc, latexmk
Home-page: https://github.com/jayanthkoushik/shinymdc
License: MIT
Author: Jayanth Koushik
Author-email: mail@jkoushik.me
Requires-Python: >=3.9,<4.0
Classifier: Development Status :: 4 - Beta
Classifier: Environment :: Console
Classifier: Intended Audience :: End Users/Desktop
Classifier: License :: OSI Approved :: MIT License
Classifier: Natural Language :: English
Classifier: Operating System :: OS Independent
Classifier: Programming Language :: Python :: 3
Classifier: Programming Language :: Python :: 3.9
Classifier: Programming Language :: Python :: 3.10
Classifier: Programming Language :: Python :: 3.11
Classifier: Topic :: Utilities
Requires-Dist: corgy[colors] (>=8.1.1,<9.0.0)
Requires-Dist: pyyaml (>=6.0,<7.0)
Project-URL: Repository, https://github.com/jayanthkoushik/shinymdc
